pyproject.toml
dainik/__init__.py
dainik/git_utils.py
dainik/lmao_client.py
dainik/src.py
dainik/utils.py
dainik/hyperopt/__init__.py
dainik/hyperopt/base.py
dainik/hyperopt/grid_sampler.py
dainik/hyperopt/opt_types.py
dainik/hyperopt/random_sampler.py
dainik/metrics/__init__.py
dainik/metrics/asgi.py
dainik/metrics/system.py
dainik/proto/lmao_pb2.py
dainik/yql/__init__.py
dainik/yql/__main__.py
dainik/yql/common.py
dainik/yql/main.py
dainik/yql/rest_pb2.py
lmao.egg-info/PKG-INFO
lmao.egg-info/SOURCES.txt
lmao.egg-info/dependency_links.txt
lmao.egg-info/top_level.txt