Metadata-Version: 2.1
Name: lmao
Version: 1.18
Summary: Client library for working with NimbleBox LMAO
Author-email: Yash Bonde <bonde.yash97@gmail.com>
Project-URL: Homepage, https://github.com/NimbleBoxAI/nbox
Classifier: Programming Language :: Python :: 3
Classifier: License :: OSI Approved :: MIT License
Classifier: Operating System :: OS Independent
Requires-Python: >=3.7
